{
    "name": "ICEshop",
    "author": "Brendan Coles <bcoles@gmail.com>",
    "version": "0.1",
    "description": "ICEshop e-commerce",
    "website": "http://www.iceshop.nl/",
    "matches": [
        {
            "text": "<p id=\"power_by\"><a href=\"http://www.iceshop.nl\" target=\"_blank\">Powered by ICEshop</a></p>"
        },
        {
            "text": "Powered by <a class=\"link copyright02\" href=\"http://www.iceshop.nl/\" target=\"_blank\">ICEshop</a>"
        },
        {
            "text": "<dl class=\"box boxLogo  box02 iceshop\">"
        }
    ]
}
