{
    "name": "phpMySport",
    "author": "Brendan Coles <bcoles@gmail.com>",
    "version": "0.1",
    "description": "PhpMySport is an open source software designed for all sport clubs and leagues which want to easily create and manage their website.",
    "website": "phpmysport.sourceforge.net",
    "matches": [
        {
            "text": "Powered by phpMySport <a href=\"http://phpmysport.sourceforge.net\" title=\"phpMySport\">"
        },
        {
            "text": "<a href=\"http://phpmysport.sourceforge.net\" title=\"phpMySport\">",
            "certainty": 25
        },
        {
            "text": "<div id=\"footer\">R&eacute;alisation phpMySport"
        },
        {
            "text": "/tpl_image/by_phpmysport.gif\" border=\"0\""
        }
    ]
}
