{
    "name": "SiteCore",
    "author": "Bhavin Senjaliya <bhavin.senjaliya@gmail.com>, Andrew Horton",
    "version": "0.2",
    "description": "Sitecore a .NET CMS, ecommerce, and digital marketing platform.",
    "website": "http://www.sitecore.net/",
    "matches": [
        {
            "search": "headers[set-cookie]",
            "regexp": "(?-mix:^SC_ANALYTICS_)",
            "name": "SC_ANALYTICS_ cookie"
        },
        {
            "search": "headers[set-cookie]",
            "regexp": "(?-mix:^sc_expview)",
            "name": "sc_expview cookie"
        }
    ]
}
