{
    "name": "USP-Secure-Login-Service",
    "author": "Brendan Coles <bcoles@gmail.com>, Andrew Horton",
    "version": "0.2",
    "description": "United Security Providers (USP; previously known as Tetrade) Secure Login Service (SLS) Framework. The SLS works alongside the USP Secure Entry Server (SES) which functions as a Reverse-Proxy and Web Application Firewall (WAF) and also fulfills the role of user authentication.",
    "website": "http://www.united-security-providers.com/",
    "matches": [
        {
            "text": "<!-- Optional: If browser does not support Javascript, load URL xyz -->"
        },
        {
            "text": "<!-- SLS JavaScripts -->"
        },
        {
            "text": "<form action=\"auth\" method=\"post\" name=\"LoginForm\" onsubmit=\"return checkFormSubmit();\" >"
        },
        {
            "certainty": 75,
            "regexp": "(?-mix:<input name=\"currentRequestedPage\" type=\"hidden\" value=\"[^\"]+\" \\/><\\/form>)"
        },
        {
            "search": "headers[slsstatus]",
            "regexp": "(?-mix:^([\\d]+)$)"
        },
        {
            "search": "headers[set-cookie]",
            "regexp": "(?-mix:SLSLanguage=([a-z]{2,3});)"
        },
        {
            "search": "headers[set-cookie]",
            "module": "zzzzzz",
            "regexp": "(?-mix:SCDID_S=[^;\\s\\$]{54}\\$\\$;)"
        }
    ]
}
